LICENSE
README.md
setup.py
nsubdomain_finder/__init__.py
nsubdomain_finder/__main__.py
nsubdomain_finder/console.py
nsubdomain_finder.egg-info/PKG-INFO
nsubdomain_finder.egg-info/SOURCES.txt
nsubdomain_finder.egg-info/dependency_links.txt
nsubdomain_finder.egg-info/entry_points.txt
nsubdomain_finder.egg-info/requires.txt
nsubdomain_finder.egg-info/top_level.txt