Metadata-Version: 2.1
Name: nsubdomain-finder
Version: 0.0.4
Summary: Perform dns-bruteforce for enumerating subdomains using nmap tool
Home-page: https://github.com/Simatwa/nsubdomain-finder
Author: Smartwa
Author-email: simatwacaleb@proton.me
Maintainer: Smartwa
License: MIT
Project-URL: Bug Report, https://github.com/Simatwa/nsubdomain-finder/issues/new
Project-URL: Homepage, https://github.com/Simatwa/nsubdomain-finder
Project-URL: Source Code, https://github.com/Simatwa/nsubdomain-finder
Project-URL: Issue Tracker, https://github.com/Simatwa/nsubdomain-finder/issues
Project-URL: Download, https://github.com/Simatwa/nsubdomain-finder/releases
Project-URL: Documentation, https://github.com/Simatwa/nsubdomain-finder/blob/main/README.md
Keywords: subdomain,subdomain-finder,nsubdomain-finder
Classifier: License :: OSI Approved :: MIT License
Classifier: Intended Audience :: Developers
Classifier: License :: Free For Home Use
Classifier: Programming Language :: Python
Classifier: Topic :: Software Development :: Libraries :: Python Modules
Classifier: Programming Language :: Python :: 3 :: Only
Classifier: Programming Language :: Python :: 3.10
Classifier: Programming Language :: Python :: 3.10
Classifier: Programming Language :: Python :: 3.11
Classifier: Programming Language :: Python :: 3.12
Requires-Python: >=3.9
License-File: LICENSE
Provides-Extra: cli
Requires-Dist: rich==13.3.4; extra == "cli"
